pycalibre/__init__.py
pycalibre/library.py
pycalibre/models/__init__.py
pycalibre/models/associations.py
pycalibre/models/base.py
pycalibre/models/book.py
pycalibre/models/comment.py
pycalibre/models/custom.py
pycalibre/models/entities.py
pycalibre/models/enums.py
pycalibre/models/format.py
pycalibre/models/identifier.py
pycalibre/models/mixins.py
pycalibre-0.1.0.dist-info/LICENSE
pycalibre-0.1.0.dist-info/METADATA
pycalibre-0.1.0.dist-info/WHEEL
pycalibre-0.1.0.dist-info/RECORD
