Metadata-Version: 2.3
Name: pycalibre
Version: 0.1.0
Summary: A Python library for interacting with a Calibre ebook library.
License: MIT
Keywords: calibre,ebook,library,python
Author: Joe Geldart
Author-email: joe@joegeldart.com
Requires-Python: >=3.11,<4.0
Classifier: Development Status :: 3 - Alpha
Classifier: License :: OSI Approved :: MIT License
Classifier: Operating System :: OS Independent
Classifier: Programming Language :: Python :: 3
Classifier: Programming Language :: Python :: 3.11
Classifier: Programming Language :: Python :: 3.12
Classifier: Programming Language :: Python :: 3.13
Requires-Dist: dateparser (>=1.2.1,<2.0.0)
Requires-Dist: sqlalchemy (>=2.0.39,<3.0.0)
Requires-Dist: types-dateparser (>=1.2.0.20250208,<2.0.0.0)
Project-URL: Homepage, https://github.com/jgeldart/pycalibre
Project-URL: Repository, https://github.com/jgeldart/pycalibre
